data_loader_part/__init__.py
data_loader_part/data_reader.py
data_loader_part/data_writer.py
DataLoader_Part-0.1.0.dist-info/METADATA
DataLoader_Part-0.1.0.dist-info/WHEEL
DataLoader_Part-0.1.0.dist-info/top_level.txt
DataLoader_Part-0.1.0.dist-info/RECORD
