Metadata-Version: 2.1
Name: DataLoader-Part
Version: 0.1.0
Summary: Data Loader Python package
Home-page: UNKNOWN
Author: Ali Rahmati
Author-email: alirahmati@outlook.com
License: BSD 2-clause
Platform: UNKNOWN
Classifier: Programming Language :: Python :: 3
Classifier: License :: OSI Approved :: MIT License
Classifier: Operating System :: OS Independent
Requires-Dist: pandas
Requires-Dist: json5
